{"VX5ucbR5PxVqZ88hgLjlLw==":"stremberg-122x122.jpg","IP8Eaqx/qtPTLBfqWq6Clw==":"p6240134%20-%20%D0%B2%D1%8B%D1%80%D0%B5%D0%B7%D0%B0%D0%BD%D0%BE%20(250%D1%85250)%20-%20%D0%B3%D0%BE%D1%82%D0%BE%D0%B2%D0%BE-122x122.jpg","nda9UDs0F5zazPHOHFYJfQ==":"bg-1-1920x430.jpg","blpIIT5D5UY3gvrXwq8eTg==":"060%20o6nm390-3326x2218.jpg","/pscwuasIBQrRCDGivK0Pg==":"223%20188-2000x1337.jpg","R/tVf3eFdLbqNvEYRf+M9w==":"216%20374417__-1254x837.jpg","IDYaAkB/8mZd6coQzBXdOQ==":"216%20374417__-1920x1281.jpg","ZBIm+8KKcjuZXhP+teT6Wg==":"216%20374417__-1332x889.jpg","B967gQDlJzWv3R5k1TeCrw==":"st-122x122.jpg","pa5Dkwo/T1qgW/t0h+fQvA==":"background5.jpg","ksufNbi4jQqN1gPM4pD3Rw==":"s124-598x598.jpg","8MmhUpgQh7ynIfrzBa+tKw==":"s055-598x398.jpg","Kx80Jr0FP7bTeS6NVBrvdA==":"s140-616x393.jpg","ItPU0TAG6DC4PnKmpPIB3Q==":"s047-616x409.jpg","zCcD5ckcsK/j97aYH6Adrg==":"s006-616x616.jpg","pU3xS7bYIfFECK+SMgPRsA==":"strem-860x860.jpg","F65zdXaHT0rkeVQb60LjnA==":"dvd_014_550x550-72-550x550.jpg","atHFPgcNS2k0+SkE5Iqu1w==":"dvd_008_550x550-72-550x550.jpg","KyRxvqiVP42zGFCoZXWi7A==":"dvd_025_550x550-72-550x550.jpg","abfu8hdq5p8erfJR8nc3PA==":"dvd_022_550x550-72-550x550.jpg","4EnQ5uZlOCznFuE4DWzx3g==":"dvd_010_550x550-72-550x550.jpg","3LCVrycatCUz+f5+4+Yelg==":"dvd_023_550x550-72-550x550.jpg","FT7l/8poqFUZqvFKrPZGkA==":"dvd_016_550x550-72-550x550.jpg","ggXYp5xUXxMGm52jvpQsIA==":"dvd_019_550x550-72-550x550.jpg","seXskLqh+fOdU9fUWHpmfg==":"dvd_018_550x550-72-550x550.jpg","4NE6M82JRS7DOCcTKBl3zQ==":"dvd_001_550x550-72-550x550.jpg","TOhJGIYdeoVSnI9tSsC69Q==":"box_028_00%20%D1%82%D0%B5%D0%BD%D1%8C,%20%D1%81%D0%B2%D0%B5%D0%B4%D0%B5%D0%BD%D0%BE,%20%D0%BE%D0%B1%D1%80%D0%B5%D0%B7%20(%D0%B2%D1%8B%D1%81%20550,%2072)-490x550.jpg","KPJUw6F3pfPKR1QAODrUyA==":"box_026_00%20%D1%82%D0%B5%D0%BD%D1%8C,%20%D1%81%D0%B2%D0%B5%D0%B4%D0%B5%D0%BD%D0%BE,%20%D0%BE%D0%B1%D1%80%D0%B5%D0%B7%20(%D0%B2%D1%8B%D1%81%20550,%2072)-490x550.jpg","BuM0DSjxOmoH+eIkC4E6Fw==":"box_025_00%20%D1%82%D0%B5%D0%BD%D1%8C,%20%D1%81%D0%B2%D0%B5%D0%B4%D0%B5%D0%BD%D0%BE,%20%D0%BE%D0%B1%D1%80%D0%B5%D0%B7%20(%D0%B2%D1%8B%D1%81%20550,%2072)-490x550.jpg","k+rEqU1Gqj2faO3wjERI8A==":"box_025_dvd_550x550-72-550x550.jpg","ePYO/5VtcftglDw2hzi6+w==":"box_024_00%20%D1%82%D0%B5%D0%BD%D1%8C,%20%D1%81%D0%B2%D0%B5%D0%B4%D0%B5%D0%BD%D0%BE,%20%D0%BE%D0%B1%D1%80%D0%B5%D0%B7%20(%D0%B2%D1%8B%D1%81%20550,%2072)-490x550.jpg","2N1xir6TVjnUUCHsNyuGvA==":"box_023_00%20%D1%82%D0%B5%D0%BD%D1%8C,%20%D1%81%D0%B2%D0%B5%D0%B4%D0%B5%D0%BD%D0%BE,%20%D0%BE%D0%B1%D1%80%D0%B5%D0%B7%20(%D0%B2%D1%8B%D1%81%20550,%2072)-490x550.jpg","ItgTeZERgeifR8uGy1soQw==":"box_022_00%20%D1%82%D0%B5%D0%BD%D1%8C,%20%D1%81%D0%B2%D0%B5%D0%B4%D0%B5%D0%BD%D0%BE,%20%D0%BE%D0%B1%D1%80%D0%B5%D0%B7%20(%D0%B2%D1%8B%D1%81%20550,%2072)-490x550.jpg","scoT/12OWJS45riTD20f/Q==":"box_019_00%20%D1%82%D0%B5%D0%BD%D1%8C,%20%D1%81%D0%B2%D0%B5%D0%B4%D0%B5%D0%BD%D0%BE,%20%D0%BE%D0%B1%D1%80%D0%B5%D0%B7%20(%D0%B2%D1%8B%D1%81%20550,%2072)-490x550.jpg","vj1Qu5dDXGYgdyToYmrvZw==":"box_015_00_550%20%D1%82%D0%B5%D0%BD%D1%8C,%20%D1%81%D0%B2%D0%B5%D0%B4%D0%B5%D0%BD%D0%BE,%20%D0%BE%D0%B1%D1%80%D0%B5%D0%B7%20(%D0%B2%D1%8B%D1%81%20550,%2072)-490x550.jpg","Y7h/esFRy4PfnA/LxUOTdw==":"box_014_00_550%20%D1%82%D0%B5%D0%BD%D1%8C,%20%D1%81%D0%B2%D0%B5%D0%B4%D0%B5%D0%BD%D0%BE,%20%D0%BE%D0%B1%D1%80%D0%B5%D0%B7%20(%D0%B2%D1%8B%D1%81%20550,%2072)-490x550.jpg","BybBVJq1Yz73ey9zVygQLg==":"box_028_dvd_03-550-616x507.jpg","iFBfDdeSZKCn39QRGcbQdQ==":"dvd_011_550x550-72-550x550.jpg","5TnuckSx1QevI5SqqJZjDQ==":"dvd_009_550x550-72-550x550.jpg","p5aQzTuDULogUD4K9bhzNQ==":"dvd_028-5-547x420.jpg","65Z7LmV7QT5Ca1t3eRPrLw==":"dvd_006_550x550-72-550x550.jpg","Ao/TuwGiiNJGn8M3JpdsAA==":"dvd_002_550x550-72-550x550.jpg","f0zqRXKRaF1cUGHrfzvk1A==":"dvd_020_550x550-72-550x550.jpg","XZhPh++H4NP1nm38OoOhCw==":"dvd_012_550x550-72-550x550.jpg","i4aeJYRnk6dwlC4KHnnBwg==":"dvd_013_550x550-72-550x550.jpg","q273asYg3DFgwWS8CLi8Nw==":"str_moscow_1995-1-800x533.jpg","Rt9FR+SljjsVWibWGZ6oaA==":"str_moscow_1995-2-626x752.jpg","DxhNz8nGn4n8jLxibj177g==":"dvd_10_oblozhek-860x410.jpg","ddk7KIlY4nG/0Exrr6IqOg==":"box_019_00%20%D1%82%D0%B5%D0%BD%D1%8C,%20%D1%81%D0%B2%D0%B5%D0%B4%D0%B5%D0%BD%D0%BE,%20%D0%BE%D0%B1%D1%80%D0%B5%D0%B7%20(%D0%B2%D1%8B%D1%81%20750,%2072)-669x750.jpg","deQkSizcsIP50OYO97ksEg==":"s065-616x400.jpg","tvq74qEe5edTE8HtBWzYUw==":"s149-616x411.jpg","ldA8ahhowc6kYBdcyZcY2w==":"s150-616x364.jpg","K1jGOUb2/3m4rvB/sNnP6A==":"s151-616x410.jpg","hvmq/rwOQ98nJy5iztA2ZA==":"s152-616x410.jpg","1+WbZR4DHriRsa0QlP66BA==":"s153-616x410.jpg","SrdyPSP5VI6mNHY/goOloA==":"s154-616x410.jpg","WU04hopRgIgVQHrGb0e/5g==":"s155-616x467.jpg","Por8P6HkK1G/nCqPH89rtg==":"s156-616x447.jpg","laloAmpq/iAF5QpE+6wBeg==":"s033-616x410.jpg","IH42tXY+0VwFX52+47iIbQ==":"s020-616x410.jpg","NRx8B9Hw53/gFqw5M6bVqg==":"s157-616x467.jpg","CjxoSntN/4CffaJB403LOg==":"s159-616x410.jpg","mkv7Rm+nLMV7tSCSlmddqQ==":"s160-553x320.jpg","hk9TQ3F5G5P2lnUZDOaIfg==":"s161-616x410.jpg","jqCCsEhGybfFzoOIgEg7Pw==":"s162-580x352.jpg","2DUq32J/6jQL76hmMThpxQ==":"s164-616x382.jpg","KgrCOdx7T1zs171bCD/cyA==":"s082-616x410.jpg","8SwsM/4nWO7AjfVvNjqHPw==":"s165-616x410.jpg","rL/dB83U0I9byqdrTsgoSg==":"s058-626x417.jpg","UAc7kepzJPkrSn4uqTRvmw==":"background4.jpg","GcZOJT9iXoG5XumL1bkAFw==":"s083-626x417.jpg","qaH+N6mKXyiYk3XWAPODkA==":"s186-626x417.jpg","6wZ2kJPSbMZcS0roMzGgBA==":"s055-626x417.jpg","jauzBc7qJ4GHag2hzbJ96w==":"s033-626x417.jpg","GBr9CtW8y3BC2swfsVeCGw==":"s182-626x417.jpg","ZC1h27R5DqMKYhuKcuGg+Q==":"s179-626x417.jpg","h/JFcEBtrbwgVT7cQnwJAg==":"s188-626x417.jpg","5OR8musj5r0NyFVnAEpy2Q==":"s159-626x417.jpg","kubBLjQ5CLYpap29p4RKIA==":"s161-626x417.jpg","flwVnQW0/apYhMz5ESjtLw==":"s153-626x417.jpg","jKdNfrKGvbSp9LxzKogJUA==":"s065-626x417.jpg","ljWbqHqNzrjBLWK+ozXUqA==":"s162-626x417.jpg","ao7L35XRL1voM3vSKg76fA==":"s190-626x417.jpg","aUrSmkXfaTAFveN1z51uXA==":"s009-626x417.jpg","1v/vn2JAwnI4vsbJo2woQQ==":"s152-626x417.jpg","sUZCmBZ44UpqAbdr5rPc3Q==":"s172s-626x417.jpg","eC2PmJ+ZdoyU1bpIXz7+ZA==":"s151-626x417.jpg","QsHJLL5HsF+IL2fmu3NIlA==":"s125-626x417.jpg","wDnQ3ZtHiLTsthupnxTNYA==":"s082-626x417.jpg","IafqfBDv9RPIodX3qq+tZA==":"s165-626x417.jpg","6+wih4SgFSLjLj4Zo860tw==":"s044-626x417.jpg","2iPHioTlIjuqa0vyAiqBFw==":"s164-616x417.jpg","A0IlBXO6+au9OBApjzW8mQ==":"s150-626x417.jpg","DCqSpRYf77NkmwJFsSkFgQ==":"s149-626x417.jpg","t2VidVnRrOFR1vzkIzM4Jg==":"s192-626x417.jpg","Sw6jtM2hyYcQ2M+ch1ca7w==":"s193-626x417.jpg","O0hVG2JPL4ZbsJk95TdHEQ==":"s194-626x417.jpg","QI1Ik9EHCX5jTnKRkfmhTw==":"s196-626x417.jpg","H3Tv+P3pNfqiCqMfJd5OXA==":"s198s-626x417.jpg","MnJF9an045L3epCOfPjK4g==":"s199-626x417.jpg","RwLld8+jFivz1aq1oXaf3w==":"s199-1-626x417.jpg","Thew1bwkQc38xtcoS7rP2Q==":"s201s-626x417.jpg","ByVNpI2qeIUSgdGJjEGsdw==":"foto_626x417-616x410.jpg","BDew/c9OzhSBybyVdf8ksw==":"s011-626x417.jpg","hLvvzn6hzgAdelTpf3aT7Q==":"s202-626x417.jpg","wXBk+DbH3G3u2CH9+6I2tg==":"s203-626x417.jpg","1Ay4GlpoQGbZfMLm4eUjPw==":"s204-626x417.jpg","mtdlJd8cr/37oGDspBXLlA==":"s204-1-626x417.jpg","Wwc5bw98BK/5MMl1sOnzZQ==":"s204s-626x417.jpg","DAy10t4m0CJkmR7Lvx/l+w==":"s204s-1-626x417.jpg","uYlH/D5Ltz+K6Bzwtf27VQ==":"post-18-570x321.jpg","qu4TSofgj68xX0HcI+HZcQ==":"post-15-570x475.jpg","Btu+IEd1AC3WqlsjnyzFdw==":"post-22-616x443.jpg","ZI80l8uGcHi4mimX7pUllw==":"post_018s-476x321.jpg","nWbxOM5abDqoXKOfaPvLxA==":"s205-626x417.jpg","oKtzxJEHeTM9ou0y3Kx1fg==":"s158-626x417.jpg","hj2JLR/zlvKJMLzdkKIhJQ==":"s207s-626x417.jpg","FIpeg6biFkr498H7t2mdkQ==":"s208-626x417.jpg","MC2X/VxJ0fNxJymjBjsV3A==":"s242s-616x410.jpg","bDXDdEPJLuk0a7yGhUc+qg==":"s218s-616x410.jpg","msqP0TR9xWeVJgU0sZbx4w==":"s218ss-616x410.jpg","Zh+3A18jqNyow8vO1PlpSw==":"s242s-1-616x410.jpg","zyYgYY6wxgUiBr+jvx7knQ==":"s218ss-1-616x410.jpg","p+kDd89vEAoC9PGkaYP/EA==":"strem_krug-460x460.jpg"}